tv2/__init__.py
tv2/notebook.py
tv2/urwid_ui.py
tv2-0.2.4.data/scripts/tv2
tv2-0.2.4.dist-info/LICENSE.txt
tv2-0.2.4.dist-info/METADATA
tv2-0.2.4.dist-info/WHEEL
tv2-0.2.4.dist-info/top_level.txt
tv2-0.2.4.dist-info/RECORD
