Metadata-Version: 2.1
Name: tv2
Version: 0.2.4
Summary: A fast note-taking app for the UNIX terminal
Home-page: http://github.com/makyo/tv2/
Author: Sean Hammond, Vincent Perricone, Madison Scott-Clary
Author-email: makyo+tv2@drab-makyo.com
License: GNU General Public License, Version 3
Platform: UNKNOWN
Classifier: Development Status :: 5 - Production/Stable
Classifier: Environment :: Console
Classifier: License :: OSI Approved :: GNU General Public License v3 (GPLv3)
Classifier: Natural Language :: English
Classifier: Operating System :: MacOS
Classifier: Operating System :: POSIX
Classifier: Programming Language :: Python :: 2
Classifier: Programming Language :: Python :: 3
Requires-Dist: urwid (==2.0.1)
Requires-Dist: chardet (==3.0.4)
Requires-Dist: six (==1.12.0)
